came_domotic_unofficial/__init__.py
came_domotic_unofficial/auth.py
came_domotic_unofficial/came_domotic_api.py
came_domotic_unofficial/const.py
came_domotic_unofficial/errors.py
came_domotic_unofficial/models/__init__.py
came_domotic_unofficial/models/base.py
came_domotic_unofficial/models/light.py
came_domotic_unofficial/models/update.py
came_domotic_unofficial-1.0.0rc32.dist-info/LICENSE
came_domotic_unofficial-1.0.0rc32.dist-info/METADATA
came_domotic_unofficial-1.0.0rc32.dist-info/WHEEL
came_domotic_unofficial-1.0.0rc32.dist-info/RECORD
