Metadata-Version: 2.1
Name: came_domotic_unofficial
Version: 1.0.0rc32
Summary: Python library to interact with a CAME ETI/Domo domotic server.
Home-page: https://github.com/camedomotic-unofficial/came_domotic_unofficial
License: Apache-2.0
Keywords: CAME,ETI/Domo,domotic,home automation,home assistant,home-assistant
Author: camedomotic-unofficial
Author-email: camedomotic-unofficial@gmail.com
Maintainer: camedomotic-unofficial
Maintainer-email: camedomotic-unofficial@gmail.com
Requires-Python: >=3.12,<4.0
Classifier: Development Status :: 4 - Beta
Classifier: Intended Audience :: Developers
Classifier: License :: OSI Approved :: Apache Software License
Classifier: Operating System :: OS Independent
Classifier: Programming Language :: Python :: 3
Classifier: Programming Language :: Python :: 3.12
Classifier: Topic :: Home Automation
Classifier: Topic :: Software Development :: Libraries :: Python Modules
Requires-Dist: aiohttp (>=3.9.3,<4.0.0)
Requires-Dist: asyncio (>=3.4.3,<4.0.0)
Requires-Dist: cryptography (>=42.0.7,<43.0.0)
Requires-Dist: requests (>=2.32.2,<3.0.0)
Project-URL: Bug tracker, https://github.com/camedomotic-unofficial/came_domotic_unofficial/issues
Project-URL: Documentation, https://came-domotic-unofficial.readthedocs.io/en/latest/index.html
Project-URL: Repository, https://github.com/camedomotic-unofficial/came_domotic_unofficial.git
